udacity_pa/__init__.py
udacity_pa/__main__.py
udacity_pa/projectassistant.py
udacity_pa/sessionbuilder.py
udacity_pa/udacity.py
udacity_pa/uploadcallbacks.py
udacity_pa-0.2.8.dist-info/DESCRIPTION.rst
udacity_pa-0.2.8.dist-info/METADATA
udacity_pa-0.2.8.dist-info/RECORD
udacity_pa-0.2.8.dist-info/WHEEL
udacity_pa-0.2.8.dist-info/entry_points.txt
udacity_pa-0.2.8.dist-info/metadata.json
udacity_pa-0.2.8.dist-info/top_level.txt
