Metadata-Version: 2.0
Name: udacity-pa
Version: 0.2.8
Summary: CLI tool for Udacity's project assistant.
Home-page: http://github.com/udacity/udacity-pa
Author: S. Charles Brubaker
Author-email: cb@udacity.com
License: MIT
Keywords: Udacity
Platform: UNKNOWN
Requires-Dist: future
Requires-Dist: requests (>=2.2.1)
Requires-Dist: requests-toolbelt (>=0.7.0)
